pol_data_gen/DataGenerator.py
pol_data_gen/Tree.py
pol_data_gen/TreeBuild.py
pol_data_gen/TreeNodes.py
pol_data_gen/__init__.py
pol_data_gen/alreadyInitialized.py
pol_data_gen/generateCombinations.py
pol_data_gen/randomNumber.py
pol_data_gen-0.0.1.dist-info/LICENSE
pol_data_gen-0.0.1.dist-info/METADATA
pol_data_gen-0.0.1.dist-info/WHEEL
pol_data_gen-0.0.1.dist-info/top_level.txt
pol_data_gen-0.0.1.dist-info/RECORD
